solidago/__init__.py
solidago/__version__.py
solidago/judgments.py
solidago/primitives.py
solidago/privacy_settings.py
solidago/scoring_model.py
solidago/aggregation/__init__.py
solidago/aggregation/average.py
solidago/aggregation/base.py
solidago/aggregation/entitywise_qr_quantile.py
solidago/aggregation/standardized_qr_median.py
solidago/aggregation/standardized_qr_quantile.py
solidago/generative_model/__init__.py
solidago/generative_model/comparison_model.py
solidago/generative_model/engagement_model.py
solidago/generative_model/entity_model.py
solidago/generative_model/generative_model.py
solidago/generative_model/user_model.py
solidago/generative_model/vouch_model.py
solidago/pipeline/__init__.py
solidago/pipeline/inputs.py
solidago/pipeline/outputs.py
solidago/pipeline/pipeline.py
solidago/post_process/__init__.py
solidago/post_process/base.py
solidago/post_process/no_post_process.py
solidago/post_process/squash.py
solidago/preference_learning/__init__.py
solidago/preference_learning/base.py
solidago/preference_learning/comparison_learning.py
solidago/preference_learning/generalized_bradley_terry.py
solidago/preference_learning/hookean_model.py
solidago/preference_learning/lbfgs_generalized_bradley_terry.py
solidago/scaling/__init__.py
solidago/scaling/base.py
solidago/scaling/compose.py
solidago/scaling/mehestan.py
solidago/scaling/no_scaling.py
solidago/scaling/quantile_zero_shift.py
solidago/scaling/standardize.py
solidago/solvers/dichotomy.py
solidago/solvers/optimize.py
solidago/trust_propagation/__init__.py
solidago/trust_propagation/base.py
solidago/trust_propagation/lipschitrust.py
solidago/trust_propagation/no_trust_propagation.py
solidago/trust_propagation/noop.py
solidago/trust_propagation/trust_all.py
solidago/utils/date.py
solidago/utils/pairs.py
solidago/voting_rights/__init__.py
solidago/voting_rights/affine_overtrust.py
solidago/voting_rights/base.py
solidago/voting_rights/compute_voting_rights.py
solidago/voting_rights/is_trust.py
solidago-0.5.0.dist-info/METADATA
solidago-0.5.0.dist-info/WHEEL
solidago-0.5.0.dist-info/licenses/LICENSE
solidago-0.5.0.dist-info/licenses/LICENSE.LESSER
solidago-0.5.0.dist-info/RECORD
