Metadata-Version: 2.4
Name: solidago
Version: 0.5.0
Summary: A toolbox for Solid Algorithmic Governance
Project-URL: Homepage, https://github.com/tournesol-app/tournesol/tree/main/solidago
Project-URL: Bug Tracker, https://github.com/tournesol-app/tournesol/issues
Project-URL: Documentation, https://solidago.tournesol.app
Author-email: Tournesol Association <hello@tournesol.app>
License-Expression: LGPL-3.0-or-later
License-File: LICENSE
License-File: LICENSE.LESSER
Keywords: collaborative recommendations,comparison based,judgement aggregation,mehestan,tournesol
Classifier: License :: OSI Approved :: GNU Lesser General Public License v3 or later (LGPLv3+)
Classifier: Operating System :: OS Independent
Classifier: Programming Language :: Python :: 3
Requires-Python: >=3.13
Requires-Dist: numba==0.63.*
Requires-Dist: numpy>=2.3
Requires-Dist: pandas<3.0,>=1.5.3
Provides-Extra: docs
Requires-Dist: markdown-include==0.8.1; extra == 'docs'
Requires-Dist: mkdocs-material==9.*; extra == 'docs'
Requires-Dist: mkdocstrings[python]==0.*; extra == 'docs'
Provides-Extra: test
Requires-Dist: pytest<9.0.0,>=7.1.3; extra == 'test'
Provides-Extra: torch
Requires-Dist: torch<3,>=2.2; extra == 'torch'
